pavefinancial/__init__.py
pavefinancial-0.0.1.dist-info/METADATA
pavefinancial-0.0.1.dist-info/WHEEL
pavefinancial-0.0.1.dist-info/top_level.txt
pavefinancial-0.0.1.dist-info/RECORD
