Metadata-Version: 2.1
Name: pavefinancial
Version: 0.0.1
Summary: Please visit us at pave.dev
Home-page: UNKNOWN
License: UNKNOWN
Platform: UNKNOWN
Classifier: Topic :: Software Development
Requires-Python: >=3.6
